<?xml version="1.0" encoding="windows-1251"?>
<WLDevice>
    <WLM35A UID96="">
        <Modules>
            <WLModuleConnect timeoutConnect_ms="5000" timeHeart_ms="0"/>
            <WLModuleIOPut>
                <inputs size="7" inv=""/>
                <outputs size="13" inv="1,2,4"/>
            </WLModuleIOPut>
            <WLModuleAxis size="4" inEMGStop="0" inSDStop="0" Fmax="0">
                <Axis index="0" kSTCurve="0" delaySCurve="0" typePulse="0" outSDinv="0" inORG="0" inPEL="0" actInPEL="0" inMEL="0" actInMEL="0" inALM="0" actInALM="0" outRALM="0" outENB="0"/>
                <Axis index="1" kSTCurve="0" delaySCurve="0" typePulse="0" outSDinv="0" inORG="0" inPEL="0" actInPEL="0" inMEL="0" actInMEL="0" inALM="0" actInALM="0" outRALM="0" outENB="0"/>
                <Axis index="2" kSTCurve="0" delaySCurve="0" typePulse="0" outSDinv="0" inORG="0" inPEL="0" actInPEL="0" inMEL="0" actInMEL="0" inALM="0" actInALM="0" outRALM="0" outENB="0"/>
                <Axis index="3" kSTCurve="0" delaySCurve="0" typePulse="0" outSDinv="0" inORG="0" inPEL="0" actInPEL="0" inMEL="0" actInMEL="0" inALM="0" actInALM="0" outRALM="0" outENB="0"/>
            </WLModuleAxis>
            <WLModulePWM>
                <outputs size="3">
                    <PWM index="0" Freq="8000" inv="1"/>
                    <PWM index="1" Freq="1000" inv="0"/>
                    <PWM index="2" Freq="2000" inv="0"/>
                </outputs>
            </WLModulePWM>
            <WLModulePlanner SmoothAngGr="15" KFpause="0.25" SOut="0,255" accSOut="0.0002" decSOut="-0.0005" inProbe="0" inPause="0"/>
        </Modules>
    </WLM35A>
</WLDevice>
